{
  "chart_id": "382FZ-RNUT-1M-20260223-001",
  "setup_name": "382 + Flip Zone",
  "canonical_key": "382_flip_zone",
  "token": "RNUT",
  "timeframe": "1M",
  "date": "2026-02-23",
  "fib_depth": "382",
  "structure_state": "Trained",
  "rsi_behavior": "",
  "whale_conviction": false,
  "violent_mode": false,
  "outcome_percentage": 50,
  "expansion_time_minutes": 0,
  "screenshot_fingerprint_id": "AgACAgEAAxkBAAIE72mb7_c9y-c9yNRA6b_x34JH5YMnAALaC2sbHBvhRDdpT_lvb3GCAQADAgADdwADOgQ",
  "notes": "CLEAN STRUCTURE HIGH VOLUME",
  "trained_at": "2026-02-23T06:14:32.859216"
}